rrg12/__init__.py
rrg12/custom.py
rrg12/enums.py
rrg12/modbus.py
rrg12-1.0.4.dist-info/LICENSE
rrg12-1.0.4.dist-info/METADATA
rrg12-1.0.4.dist-info/WHEEL
rrg12-1.0.4.dist-info/top_level.txt
rrg12-1.0.4.dist-info/RECORD
