Metadata-Version: 2.1
Name: rrg12
Version: 1.0.4
Summary: Package to communicate with RRG flow regulators by eltochpribor
Home-page: https://github.com/dydyamotya/rrg12
Author: dydyamotya
Author-email: matderevenayv@yandex.ru
License: UNKNOWN
Project-URL: Bug Tracker, https://github.com/dydyamotya/rrg12/issues
Platform: UNKNOWN
Classifier: Programming Language :: Python :: 3
Classifier: License :: OSI Approved :: MIT License
Classifier: Operating System :: OS Independent
Requires-Python: >=3.6
License-File: LICENSE
Requires-Dist: pyserial
Requires-Dist: pymodbus
